[
  {
    "id": 1,
    "name": "ספורט 1",
    "url": "https://beautifulpeople.lovecdn.ru/SPORT1IL/index.fmp4.m3u8?token=85661aca6fcff75fc386afac7bbd1befcb8b950f-119432f0f95fa266775e5f0e67f35718-1764647185-1764636385",
    "image": "sport1",
    "headers": {
      "accept": "*/*",
      "referer": "https://beautifulpeople.lovecdn.ru/SPORT1IL/embed.html?token=85661aca6fcff75fc386afac7bbd1befcb8b950f-119432f0f95fa266775e5f0e67f35718-1764647185-1764636385&remote=no_check_ip",
      "origin": "https://beautifulpeople.lovecdn.ru",
      "user-agent": "Mozilla/5.0 (X11; Linux x86_64) AppleWebKit/537.36 (KHTML, like Gecko) HeadlessChrome/142.0.0.0 Safari/537.36"
    }
  },
  {
    "id": 2,
    "name": "ספורט 2",
    "url": "https://beautifulpeople.lovecdn.ru/SPORT2IL/index.fmp4.m3u8?token=f19878f1d023ca99c0cd5fa282e1f75d4e20face-ab3aa7c35212c9b33ffe7a6aafd55ef1-1764647190-1764636390",
    "image": "sport2",
    "headers": {
      "accept": "*/*",
      "referer": "https://beautifulpeople.lovecdn.ru/SPORT2IL/embed.html?token=f19878f1d023ca99c0cd5fa282e1f75d4e20face-ab3aa7c35212c9b33ffe7a6aafd55ef1-1764647190-1764636390&remote=no_check_ip",
      "origin": "https://beautifulpeople.lovecdn.ru",
      "user-agent": "Mozilla/5.0 (X11; Linux x86_64) AppleWebKit/537.36 (KHTML, like Gecko) HeadlessChrome/142.0.0.0 Safari/537.36"
    }
  },
  {
    "id": 3,
    "name": "ספורט 3",
    "url": "https://beautifulpeople.lovecdn.ru/SPORT3IL/index.fmp4.m3u8?token=b67d08b8bdada5da8db89f4fc54ca92e61ac4156-b63c697d1c1742ebe6faa3db1f152a4b-1764647195-1764636395",
    "image": "sport3",
    "headers": {
      "accept": "*/*",
      "referer": "https://beautifulpeople.lovecdn.ru/SPORT3IL/embed.html?token=b67d08b8bdada5da8db89f4fc54ca92e61ac4156-b63c697d1c1742ebe6faa3db1f152a4b-1764647195-1764636395&remote=no_check_ip",
      "origin": "https://beautifulpeople.lovecdn.ru",
      "user-agent": "Mozilla/5.0 (X11; Linux x86_64) AppleWebKit/537.36 (KHTML, like Gecko) HeadlessChrome/142.0.0.0 Safari/537.36"
    }
  },
  {
    "id": 4,
    "name": "ספורט 4",
    "url": "https://beautifulpeople.lovecdn.ru/SPORT4IL/index.fmp4.m3u8?token=0ae16e9b8eac143c4844e2d401e3d9b1a51e7eef-5673695dde75db931682aa64edaa8b9e-1764647200-1764636400",
    "image": "sport4",
    "headers": {
      "accept": "*/*",
      "referer": "https://beautifulpeople.lovecdn.ru/SPORT4IL/embed.html?token=0ae16e9b8eac143c4844e2d401e3d9b1a51e7eef-5673695dde75db931682aa64edaa8b9e-1764647200-1764636400&remote=no_check_ip",
      "origin": "https://beautifulpeople.lovecdn.ru",
      "user-agent": "Mozilla/5.0 (X11; Linux x86_64) AppleWebKit/537.36 (KHTML, like Gecko) HeadlessChrome/142.0.0.0 Safari/537.36"
    }
  },
  {
    "id": 5,
    "name": "ספורט 5",
    "url": "https://beautifulpeople.lovecdn.ru/SPORT5IL/index.fmp4.m3u8?token=8e4617de7919349d433177b8c02e6198b15897e9-947e964c8c1db383c0b34a2bf392ab57-1764647204-1764636404",
    "image": "sport5",
    "headers": {
      "accept": "*/*",
      "referer": "https://beautifulpeople.lovecdn.ru/SPORT5IL/embed.html?token=8e4617de7919349d433177b8c02e6198b15897e9-947e964c8c1db383c0b34a2bf392ab57-1764647204-1764636404&remote=no_check_ip",
      "origin": "https://beautifulpeople.lovecdn.ru",
      "user-agent": "Mozilla/5.0 (X11; Linux x86_64) AppleWebKit/537.36 (KHTML, like Gecko) HeadlessChrome/142.0.0.0 Safari/537.36"
    }
  },
  {
    "id": 6,
    "name": "ספורט 5 פלוס",
    "url": "https://beautifulpeople.lovecdn.ru/SPORT5PLUS/index.fmp4.m3u8?token=53dda1a95903a17dc04f1b060ef70971652e763b-d036e3d8d1bec646020483f7067bd31e-1764647209-1764636409",
    "image": "sport5plus",
    "headers": {
      "accept": "*/*",
      "referer": "https://beautifulpeople.lovecdn.ru/SPORT5PLUS/embed.html?token=53dda1a95903a17dc04f1b060ef70971652e763b-d036e3d8d1bec646020483f7067bd31e-1764647209-1764636409&remote=no_check_ip",
      "origin": "https://beautifulpeople.lovecdn.ru",
      "user-agent": "Mozilla/5.0 (X11; Linux x86_64) AppleWebKit/537.36 (KHTML, like Gecko) HeadlessChrome/142.0.0.0 Safari/537.36"
    }
  },
  {
    "id": 7,
    "name": "ספורט 5 לייב",
    "url": "https://beautifulpeople.lovecdn.ru/SPORT5LIVE/index.fmp4.m3u8?token=e4ffb55f8e26e4bce29f5ec78ecced1e0bdbfcb0-3ce22553b240608b498ec9068bfee1b3-1764647213-1764636413",
    "image": "sport5live",
    "headers": {
      "accept": "*/*",
      "referer": "https://beautifulpeople.lovecdn.ru/SPORT5LIVE/embed.html?token=e4ffb55f8e26e4bce29f5ec78ecced1e0bdbfcb0-3ce22553b240608b498ec9068bfee1b3-1764647213-1764636413&remote=no_check_ip",
      "origin": "https://beautifulpeople.lovecdn.ru",
      "user-agent": "Mozilla/5.0 (X11; Linux x86_64) AppleWebKit/537.36 (KHTML, like Gecko) HeadlessChrome/142.0.0.0 Safari/537.36"
    }
  },
  {
    "id": 8,
    "name": "ספורט 5 סטארס",
    "url": "https://beautifulpeople.lovecdn.ru/SPORT5STARS/index.fmp4.m3u8?token=6cb329f63db512dae8ba68989f42b34ad141c4ae-a7af8d564e1ca7f441d7df7275e459b1-1764647217-1764636417",
    "image": "sport5stars",
    "headers": {
      "accept": "*/*",
      "referer": "https://beautifulpeople.lovecdn.ru/SPORT5STARS/embed.html?token=6cb329f63db512dae8ba68989f42b34ad141c4ae-a7af8d564e1ca7f441d7df7275e459b1-1764647217-1764636417&remote=no_check_ip",
      "origin": "https://beautifulpeople.lovecdn.ru",
      "user-agent": "Mozilla/5.0 (X11; Linux x86_64) AppleWebKit/537.36 (KHTML, like Gecko) HeadlessChrome/142.0.0.0 Safari/537.36"
    }
  },
  {
    "id": 9,
    "name": "ספורט 5 גולד",
    "url": "https://beautifulpeople.lovecdn.ru/SPORT5GOLD/index.fmp4.m3u8?token=23cda6cd401cac472a2cfb2c9423f6eca4017117-2b9457e130d28bbc9f3b4c6e724c7bfa-1764647222-1764636422",
    "image": "sport5gold",
    "headers": {
      "accept": "*/*",
      "referer": "https://beautifulpeople.lovecdn.ru/SPORT5GOLD/embed.html?token=23cda6cd401cac472a2cfb2c9423f6eca4017117-2b9457e130d28bbc9f3b4c6e724c7bfa-1764647222-1764636422&remote=no_check_ip",
      "origin": "https://beautifulpeople.lovecdn.ru",
      "user-agent": "Mozilla/5.0 (X11; Linux x86_64) AppleWebKit/537.36 (KHTML, like Gecko) HeadlessChrome/142.0.0.0 Safari/537.36"
    }
  }
]