[
  {
    "id": 1,
    "name": "ספורט 1",
    "url": "https://beautifulpeople.lovecdn.ru/SPORT1IL/index.fmp4.m3u8?token=90042099211f9a07b916453be8352c667ef860b0-f36678a24404e6c6b23e9064f504c053-1759871391-1759860591",
    "image": "sport1",
    "headers": {
      "accept": "*/*",
      "referer": "https://beautifulpeople.lovecdn.ru/SPORT1IL/embed.html?token=90042099211f9a07b916453be8352c667ef860b0-f36678a24404e6c6b23e9064f504c053-1759871391-1759860591&remote=no_check_ip",
      "origin": "https://beautifulpeople.lovecdn.ru",
      "user-agent": "Mozilla/5.0 (X11; Linux x86_64) AppleWebKit/537.36 (KHTML, like Gecko) HeadlessChrome/140.0.0.0 Safari/537.36"
    }
  },
  {
    "id": 2,
    "name": "ספורט 2",
    "url": "https://beautifulpeople.lovecdn.ru/SPORT2IL/index.fmp4.m3u8?token=18e606bd02241fd0ca7e5def911e5be7fc1d4aff-f37a5b0aca830e919325dea68441410e-1759871398-1759860598",
    "image": "sport2",
    "headers": {
      "accept": "*/*",
      "referer": "https://beautifulpeople.lovecdn.ru/SPORT2IL/embed.html?token=18e606bd02241fd0ca7e5def911e5be7fc1d4aff-f37a5b0aca830e919325dea68441410e-1759871398-1759860598&remote=no_check_ip",
      "origin": "https://beautifulpeople.lovecdn.ru",
      "user-agent": "Mozilla/5.0 (X11; Linux x86_64) AppleWebKit/537.36 (KHTML, like Gecko) HeadlessChrome/140.0.0.0 Safari/537.36"
    }
  },
  {
    "id": 3,
    "name": "ספורט 3",
    "url": "https://beautifulpeople.lovecdn.ru/SPORT3IL/index.fmp4.m3u8?token=246e3a7883dcc8df33e766ce890f9e6d14fc6221-37b4cefd3ca3cd0d6a8d6f8739142206-1759871405-1759860605",
    "image": "sport3",
    "headers": {
      "accept": "*/*",
      "referer": "https://beautifulpeople.lovecdn.ru/SPORT3IL/embed.html?token=246e3a7883dcc8df33e766ce890f9e6d14fc6221-37b4cefd3ca3cd0d6a8d6f8739142206-1759871405-1759860605&remote=no_check_ip",
      "origin": "https://beautifulpeople.lovecdn.ru",
      "user-agent": "Mozilla/5.0 (X11; Linux x86_64) AppleWebKit/537.36 (KHTML, like Gecko) HeadlessChrome/140.0.0.0 Safari/537.36"
    }
  },
  {
    "id": 4,
    "name": "ספורט 4",
    "url": "https://beautifulpeople.lovecdn.ru/SPORT4IL/index.fmp4.m3u8?token=9765176ffd2c310394a885739d0fdd5d9eff57ac-7fa8aafff31442331c66575ef118315d-1759871411-1759860611",
    "image": "sport4",
    "headers": {
      "accept": "*/*",
      "referer": "https://beautifulpeople.lovecdn.ru/SPORT4IL/embed.html?token=9765176ffd2c310394a885739d0fdd5d9eff57ac-7fa8aafff31442331c66575ef118315d-1759871411-1759860611&remote=no_check_ip",
      "origin": "https://beautifulpeople.lovecdn.ru",
      "user-agent": "Mozilla/5.0 (X11; Linux x86_64) AppleWebKit/537.36 (KHTML, like Gecko) HeadlessChrome/140.0.0.0 Safari/537.36"
    }
  },
  {
    "id": 5,
    "name": "ספורט 5",
    "url": "https://beautifulpeople.lovecdn.ru/SPORT5IL/index.fmp4.m3u8?token=15812f88f4fc73850969533a3d67f79d7c4575da-fe22f1afa74fab7a6fb1420161cfa014-1759871417-1759860617",
    "image": "sport5",
    "headers": {
      "accept": "*/*",
      "referer": "https://beautifulpeople.lovecdn.ru/SPORT5IL/embed.html?token=15812f88f4fc73850969533a3d67f79d7c4575da-fe22f1afa74fab7a6fb1420161cfa014-1759871417-1759860617&remote=no_check_ip",
      "origin": "https://beautifulpeople.lovecdn.ru",
      "user-agent": "Mozilla/5.0 (X11; Linux x86_64) AppleWebKit/537.36 (KHTML, like Gecko) HeadlessChrome/140.0.0.0 Safari/537.36"
    }
  },
  {
    "id": 6,
    "name": "ספורט 5 פלוס",
    "url": "https://beautifulpeople.lovecdn.ru/SPORT5PLUS/index.fmp4.m3u8?token=9353bff67a2b1743dae510e58783e8e5fe51af3f-3aa3f6311fecee8c70c072645fc48021-1759871423-1759860623",
    "image": "sport5plus",
    "headers": {
      "accept": "*/*",
      "referer": "https://beautifulpeople.lovecdn.ru/SPORT5PLUS/embed.html?token=9353bff67a2b1743dae510e58783e8e5fe51af3f-3aa3f6311fecee8c70c072645fc48021-1759871423-1759860623&remote=no_check_ip",
      "origin": "https://beautifulpeople.lovecdn.ru",
      "user-agent": "Mozilla/5.0 (X11; Linux x86_64) AppleWebKit/537.36 (KHTML, like Gecko) HeadlessChrome/140.0.0.0 Safari/537.36"
    }
  },
  {
    "id": 7,
    "name": "ספורט 5 לייב",
    "url": "https://beautifulpeople.lovecdn.ru/SPORT5LIVE/index.fmp4.m3u8?token=b53a654593828ff51c80786fe80f40279b389f97-b3c9aa1c88d94817988ae7066b2eca83-1759871429-1759860629",
    "image": "sport5live",
    "headers": {
      "accept": "*/*",
      "referer": "https://beautifulpeople.lovecdn.ru/SPORT5LIVE/embed.html?token=b53a654593828ff51c80786fe80f40279b389f97-b3c9aa1c88d94817988ae7066b2eca83-1759871429-1759860629&remote=no_check_ip",
      "origin": "https://beautifulpeople.lovecdn.ru",
      "user-agent": "Mozilla/5.0 (X11; Linux x86_64) AppleWebKit/537.36 (KHTML, like Gecko) HeadlessChrome/140.0.0.0 Safari/537.36"
    }
  },
  {
    "id": 8,
    "name": "ספורט 5 סטארס",
    "url": "https://beautifulpeople.lovecdn.ru/SPORT5STARS/index.fmp4.m3u8?token=eef8de7eed979a5c78a57d4cc2bba8aa1568eb42-19e041cad21ca96fbcccc42770911bdd-1759871434-1759860634",
    "image": "sport5stars",
    "headers": {
      "accept": "*/*",
      "referer": "https://beautifulpeople.lovecdn.ru/SPORT5STARS/embed.html?token=eef8de7eed979a5c78a57d4cc2bba8aa1568eb42-19e041cad21ca96fbcccc42770911bdd-1759871434-1759860634&remote=no_check_ip",
      "origin": "https://beautifulpeople.lovecdn.ru",
      "user-agent": "Mozilla/5.0 (X11; Linux x86_64) AppleWebKit/537.36 (KHTML, like Gecko) HeadlessChrome/140.0.0.0 Safari/537.36"
    }
  },
  {
    "id": 9,
    "name": "ספורט 5 גולד",
    "url": "https://beautifulpeople.lovecdn.ru/SPORT5GOLD/index.fmp4.m3u8?token=5f8070655c55d22391ba3077d8dafe6217f1165a-988db61b8960ac759bfe12889d73ace6-1759871439-1759860639",
    "image": "sport5gold",
    "headers": {
      "accept": "*/*",
      "referer": "https://beautifulpeople.lovecdn.ru/SPORT5GOLD/embed.html?token=5f8070655c55d22391ba3077d8dafe6217f1165a-988db61b8960ac759bfe12889d73ace6-1759871439-1759860639&remote=no_check_ip",
      "origin": "https://beautifulpeople.lovecdn.ru",
      "user-agent": "Mozilla/5.0 (X11; Linux x86_64) AppleWebKit/537.36 (KHTML, like Gecko) HeadlessChrome/140.0.0.0 Safari/537.36"
    }
  }
]